{
	"configurations" : 
	[
		{
			"directories" : 
			[
				{
					"build" : ".",
					"jsonFile" : "directory-.-Debug-f5ebdc15457944623624.json",
					"minimumCMakeVersion" : 
					{
						"string" : "3.20"
					},
					"projectIndex" : 0,
					"source" : ".",
					"targetIndexes" : 
					[
						0,
						1,
						2,
						3,
						4,
						5,
						6
					]
				}
			],
			"name" : "Debug",
			"projects" : 
			[
				{
					"directoryIndexes" : 
					[
						0
					],
					"name" : "CFGBuilder",
					"targetIndexes" : 
					[
						0,
						1,
						2,
						3,
						4,
						5,
						6
					]
				}
			],
			"targets" : 
			[
				{
					"directoryIndex" : 0,
					"id" : "RISCVTargetParserTableGen::@6890427a1f51a3e7e1df",
					"jsonFile" : "target-RISCVTargetParserTableGen-Debug-f1e5ef54b6d367980e23.json",
					"name" : "RISCVTargetParserTableGen",
					"projectIndex" : 0
				},
				{
					"directoryIndex" : 0,
					"id" : "acc_gen::@6890427a1f51a3e7e1df",
					"jsonFile" : "target-acc_gen-Debug-f51c6133357693f04dac.json",
					"name" : "acc_gen",
					"projectIndex" : 0
				},
				{
					"directoryIndex" : 0,
					"id" : "cfg_builder::@6890427a1f51a3e7e1df",
					"jsonFile" : "target-cfg_builder-Debug-fc5dce602169191b2c20.json",
					"name" : "cfg_builder",
					"projectIndex" : 0
				},
				{
					"directoryIndex" : 0,
					"id" : "cfg_builder_skeleton::@6890427a1f51a3e7e1df",
					"jsonFile" : "target-cfg_builder_skeleton-Debug-84b37f808bd1449d01a9.json",
					"name" : "cfg_builder_skeleton",
					"projectIndex" : 0
				},
				{
					"directoryIndex" : 0,
					"id" : "clang-tablegen-targets::@6890427a1f51a3e7e1df",
					"jsonFile" : "target-clang-tablegen-targets-Debug-9cb818e062f73908e43f.json",
					"name" : "clang-tablegen-targets",
					"projectIndex" : 0
				},
				{
					"directoryIndex" : 0,
					"id" : "intrinsics_gen::@6890427a1f51a3e7e1df",
					"jsonFile" : "target-intrinsics_gen-Debug-70e2d77043e5e98ed981.json",
					"name" : "intrinsics_gen",
					"projectIndex" : 0
				},
				{
					"directoryIndex" : 0,
					"id" : "omp_gen::@6890427a1f51a3e7e1df",
					"jsonFile" : "target-omp_gen-Debug-ed194659b949c9c41ca9.json",
					"name" : "omp_gen",
					"projectIndex" : 0
				}
			]
		}
	],
	"kind" : "codemodel",
	"paths" : 
	{
		"build" : "/home/niuniu/CFG_builder/build",
		"source" : "/home/niuniu/CFG_builder"
	},
	"version" : 
	{
		"major" : 2,
		"minor" : 6
	}
}
